anclib.py
anclib-0.11.0.dist-info/LICENSE
anclib-0.11.0.dist-info/METADATA
anclib-0.11.0.dist-info/WHEEL
anclib-0.11.0.dist-info/top_level.txt
anclib-0.11.0.dist-info/RECORD
