Metadata-Version: 2.1
Name: anclib
Version: 0.11.0
Summary: (Beginning of) library for analyzing ancestral reconstructions of DNA or protein sequences
Home-page: https://github.com/agormp/anclib
Author: Anders Gorm Pedersen
Author-email: agpe@dtu.dk
Classifier: Programming Language :: Python :: 3
Classifier: License :: OSI Approved :: GNU General Public License v3 (GPLv3)
Classifier: Operating System :: OS Independent
Requires-Python: >=3.6
License-File: LICENSE
Requires-Dist: sequencelib >=2.10.0
Requires-Dist: phylotreelib >=1.24.0
Requires-Dist: numpy
Requires-Dist: pandas
Requires-Dist: rpy2
Requires-Dist: Levenshtein
